example_package_YOUR_USERNAME_HERE/__init__.py
example_package_YOUR_USERNAME_HERE/example.py
example_package_Mouritech_storage-0.0.1.dist-info/LICENCE.txt
example_package_Mouritech_storage-0.0.1.dist-info/METADATA
example_package_Mouritech_storage-0.0.1.dist-info/WHEEL
example_package_Mouritech_storage-0.0.1.dist-info/top_level.txt
example_package_Mouritech_storage-0.0.1.dist-info/RECORD
