Metadata-Version: 2.1
Name: example_package_Mouritech_storage
Version: 0.0.1
Summary: A Mouritech package
Author-email: Prasanth <kambham.prasanth@gmail.com>
Project-URL: Homepage, https://github.com/pypa/sampleproject
Project-URL: Bug Tracker, https://github.com/pypa/sampleproject/issues
Classifier: Programming Language :: Python :: 3
Classifier: License :: OSI Approved :: MIT License
Classifier: Operating System :: OS Independent
Requires-Python: >=3.7
License-File: LICENCE.txt
